{"lat": 54.7628, "lon": 16.0864, "timezone": "Europe/Copenhagen", "timezone_offset": 7200, "current": {"dt": 1620496415, "sunrise": 1620442914, "sunset": 1620499343, "temp": 44.15, "feels_like": 39.18, "pressure": 1017, "humidity": 75, "dew_point": 36.75, "uvi": 0.09, "clouds": 20, "visibility": 10000, "wind_speed": 9.04, "wind_deg": 246, "wind_gust": 9.8, "weather": [{"id": 801, "main": "Clouds", "description": "few clouds", "icon": "02d"}]}, "minutely": [{"dt": 1620496440, "precipitation": 0}, {"dt": 1620496500, "precipitation": 0}, {"dt": 1620496560, "precipitation": 0}, {"dt": 1620496620, "precipitation": 0}, {"dt": 1620496680, "precipitation": 0}, {"dt": 1620496740, "precipitation": 0}, {"dt": 1620496800, "precipitation": 0}, {"dt": 1620496860, "precipitation": 0}, {"dt": 1620496920, "precipitation": 0}, {"dt": 1620496980, "precipitation": 0}, {"dt": 1620497040, "precipitation": 0}, {"dt": 1620497100, "precipitation": 0}, {"dt": 1620497160, "precipitation": 0}, {"dt": 1620497220, "precipitation": 0}, {"dt": 1620497280, "precipitation": 0}, {"dt": 1620497340, "precipitation": 0}, {"dt": 1620497400, "precipitation": 0}, {"dt": 1620497460, "precipitation": 0}, {"dt": 1620497520, "precipitation": 0}, {"dt": 1620497580, "precipitation": 0}, {"dt": 1620497640, "precipitation": 0}, {"dt": 1620497700, "precipitation": 0}, {"dt": 1620497760, "precipitation": 0}, {"dt": 1620497820, "precipitation": 0}, {"dt": 1620497880, "precipitation": 0}, {"dt": 1620497940, "precipitation": 0}, {"dt": 1620498000, "precipitation": 0}, {"dt": 1620498060, "precipitation": 0}, {"dt": 1620498120, "precipitation": 0}, {"dt": 1620498180, "precipitation": 0}, {"dt": 1620498240, "precipitation": 0}, {"dt": 1620498300, "precipitation": 0}, {"dt": 1620498360, "precipitation": 0}, {"dt": 1620498420, "precipitation": 0}, {"dt": 1620498480, "precipitation": 0}, {"dt": 1620498540, "precipitation": 0}, {"dt": 1620498600, "precipitation": 0}, {"dt": 1620498660, "precipitation": 0}, {"dt": 1620498720, "precipitation": 0}, {"dt": 1620498780, "precipitation": 0}, {"dt": 1620498840, "precipitation": 0}, {"dt": 1620498900, "precipitation": 0}, {"dt": 1620498960, "precipitation": 0}, {"dt": 1620499020, "precipitation": 0}, {"dt": 1620499080, "precipitation": 0}, {"dt": 1620499140, "precipitation": 0}, {"dt": 1620499200, "precipitation": 0}, {"dt": 1620499260, "precipitation": 0}, {"dt": 1620499320, "precipitation": 0}, {"dt": 1620499380, "precipitation": 0}, {"dt": 1620499440, "precipitation": 0}, {"dt": 1620499500, "precipitation": 0}, {"dt": 1620499560, "precipitation": 0}, {"dt": 1620499620, "precipitation": 0}, {"dt": 1620499680, "precipitation": 0}, {"dt": 1620499740, "precipitation": 0}, {"dt": 1620499800, "precipitation": 0}, {"dt": 1620499860, "precipitation": 0}, {"dt": 1620499920, "precipitation": 0}, {"dt": 1620499980, "precipitation": 0}, {"dt": 1620500040, "precipitation": 0}], "hourly": [{"dt": 1620493200, "temp": 44.1, "feels_like": 38.59, "pressure": 1017, "humidity": 76, "dew_point": 37.02, "uvi": 0.35, "clouds": 17, "visibility": 10000, "wind_speed": 10.36, "wind_deg": 261, "wind_gust": 12.73, "weather": [{"id": 801, "main": "Clouds", "description": "few clouds", "icon": "02d"}], "pop": 0}, {"dt": 1620496800, "temp": 44.15, "feels_like": 39.18, "pressure": 1017, "humidity": 75, "dew_point": 36.75, "uvi": 0.09, "clouds": 20, "visibility": 10000, "wind_speed": 9.04, "wind_deg": 246, "wind_gust": 9.8, "weather": [{"id": 801, "main": "Clouds", "description": "few clouds", "icon": "02d"}], "pop": 0}, {"dt": 1620500400, "temp": 44.15, "feels_like": 39.15, "pressure": 1017, "humidity": 74, "dew_point": 36.41, "uvi": 0, "clouds": 36, "visibility": 10000, "wind_speed": 9.13, "wind_deg": 218, "wind_gust": 9.57, "weather": [{"id": 802, "main": "Clouds", "description": "scattered clouds", "icon": "03n"}], "pop": 0}, {"dt": 1620504000, "temp": 44.2, "feels_like": 38.98, "pressure": 1017, "humidity": 74, "dew_point": 36.46, "uvi": 0, "clouds": 52, "visibility": 10000, "wind_speed": 9.66, "wind_deg": 191, "wind_gust": 10.18, "weather": [{"id": 803, "main": "Clouds", "description": "broken clouds", "icon": "04n"}], "pop": 0}, {"dt": 1620507600, "temp": 44.33, "feels_like": 38.3, "pressure": 1017, "humidity": 73, "dew_point": 36.23, "uvi": 0, "clouds": 68, "visibility": 10000, "wind_speed": 11.97, "wind_deg": 171, "wind_gust": 13.51, "weather": [{"id": 803, "main": "Clouds", "description": "broken clouds", "icon": "04n"}], "pop": 0}, {"dt": 1620511200, "temp": 44.19, "feels_like": 37.85, "pressure": 1016, "humidity": 72, "dew_point": 35.74, "uvi": 0, "clouds": 84, "visibility": 10000, "wind_speed": 12.82, "wind_deg": 154, "wind_gust": 15.46, "weather": [{"id": 803, "main": "Clouds", "description": "broken clouds", "icon": "04n"}], "pop": 0}, {"dt": 1620514800, "temp": 43.84, "feels_like": 36.77, "pressure": 1016, "humidity": 76, "dew_point": 37.04, "uvi": 0, "clouds": 100, "visibility": 10000, "wind_speed": 14.97, "wind_deg": 151, "wind_gust": 21.43, "weather": [{"id": 804, "main": "Clouds", "description": "overcast clouds", "icon": "04n"}], "pop": 0}, {"dt": 1620518400, "temp": 44.01, "feels_like": 36.43, "pressure": 1015, "humidity": 77, "dew_point": 37.49, "uvi": 0, "clouds": 100, "visibility": 10000, "wind_speed": 17.07, "wind_deg": 158, "wind_gust": 27.4, "weather": [{"id": 804, "main": "Clouds", "description": "overcast clouds", "icon": "04n"}], "pop": 0}, {"dt": 1620522000, "temp": 44.35, "feels_like": 36.34, "pressure": 1015, "humidity": 76, "dew_point": 37.33, "uvi": 0, "clouds": 100, "visibility": 10000, "wind_speed": 19.3, "wind_deg": 160, "wind_gust": 32.1, "weather": [{"id": 804, "main": "Clouds", "description": "overcast clouds", "icon": "04n"}], "pop": 0}, {"dt": 1620525600, "temp": 44.6, "feels_like": 36.52, "pressure": 1014, "humidity": 74, "dew_point": 37.06, "uvi": 0, "clouds": 100, "visibility": 10000, "wind_speed": 19.98, "wind_deg": 159, "wind_gust": 33.06, "weather": [{"id": 804, "main": "Clouds", "description": "overcast clouds", "icon": "04n"}], "pop": 0}, {"dt": 1620529200, "temp": 44.67, "feels_like": 36.41, "pressure": 1013, "humidity": 73, "dew_point": 36.84, "uvi": 0, "clouds": 100, "visibility": 10000, "wind_speed": 20.94, "wind_deg": 168, "wind_gust": 35.16, "weather": [{"id": 804, "main": "Clouds", "description": "overcast clouds", "icon": "04d"}], "pop": 0}, {"dt": 1620532800, "temp": 44.67, "feels_like": 36.57, "pressure": 1013, "humidity": 75, "dew_point": 37.31, "uvi": 0.02, "clouds": 100, "visibility": 10000, "wind_speed": 20.18, "wind_deg": 168, "wind_gust": 30.15, "weather": [{"id": 804, "main": "Clouds", "description": "overcast clouds", "icon": "04d"}], "pop": 0.14}, {"dt": 1620536400, "temp": 43.9, "feels_like": 35.85, "pressure": 1013, "humidity": 83, "dew_point": 39.09, "uvi": 0.09, "clouds": 100, "visibility": 10000, "wind_speed": 18.84, "wind_deg": 154, "wind_gust": 30.29, "weather": [{"id": 500, "main": "Rain", "description": "light rain", "icon": "10d"}], "pop": 0.61, "rain": {"1h": 0.75}}, {"dt": 1620540000, "temp": 43.79, "feels_like": 34.74, "pressure": 1012, "humidity": 86, "dew_point": 40.05, "uvi": 0.21, "clouds": 100, "visibility": 10000, "wind_speed": 23.53, "wind_deg": 154, "wind_gust": 37.31, "weather": [{"id": 500, "main": "Rain", "description": "light rain", "icon": "10d"}], "pop": 0.93, "rain": {"1h": 0.48}}, {"dt": 1620543600, "temp": 44.44, "feels_like": 35.55, "pressure": 1012, "humidity": 85, "dew_point": 40.35, "uvi": 0.51, "clouds": 100, "visibility": 10000, "wind_speed": 23.76, "wind_deg": 158, "wind_gust": 37.02, "weather": [{"id": 500, "main": "Rain", "description": "light rain", "icon": "10d"}], "pop": 0.58, "rain": {"1h": 0.12}}, {"dt": 1620547200, "temp": 45.66, "feels_like": 37.33, "pressure": 1012, "humidity": 80, "dew_point": 40.03, "uvi": 0.81, "clouds": 100, "visibility": 10000, "wind_speed": 22.93, "wind_deg": 171, "wind_gust": 34.47, "weather": [{"id": 500, "main": "Rain", "description": "light rain", "icon": "10d"}], "pop": 0.45, "rain": {"1h": 0.11}}, {"dt": 1620550800, "temp": 46.49, "feels_like": 38.88, "pressure": 1011, "humidity": 80, "dew_point": 40.86, "uvi": 1.09, "clouds": 100, "visibility": 10000, "wind_speed": 20.6, "wind_deg": 181, "wind_gust": 31.94, "weather": [{"id": 804, "main": "Clouds", "description": "overcast clouds", "icon": "04d"}], "pop": 0.24}, {"dt": 1620554400, "temp": 47.73, "feels_like": 41.31, "pressure": 1011, "humidity": 80, "dew_point": 42.06, "uvi": 5.32, "clouds": 100, "visibility": 10000, "wind_speed": 16.82, "wind_deg": 186, "wind_gust": 27.04, "weather": [{"id": 804, "main": "Clouds", "description": "overcast clouds", "icon": "04d"}], "pop": 0.12}, {"dt": 1620558000, "temp": 49.39, "feels_like": 43.75, "pressure": 1011, "humidity": 80, "dew_point": 43.56, "uvi": 5.61, "clouds": 100, "visibility": 10000, "wind_speed": 15.46, "wind_deg": 190, "wind_gust": 22.75, "weather": [{"id": 804, "main": "Clouds", "description": "overcast clouds", "icon": "04d"}], "pop": 0.02}, {"dt": 1620561600, "temp": 50.32, "feels_like": 48.81, "pressure": 1011, "humidity": 80, "dew_point": 44.58, "uvi": 5.24, "clouds": 99, "visibility": 10000, "wind_speed": 14.25, "wind_deg": 192, "wind_gust": 19.13, "weather": [{"id": 804, "main": "Clouds", "description": "overcast clouds", "icon": "04d"}], "pop": 0.01}, {"dt": 1620565200, "temp": 51.04, "feels_like": 49.6, "pressure": 1011, "humidity": 80, "dew_point": 45.37, "uvi": 4.29, "clouds": 96, "visibility": 10000, "wind_speed": 13.58, "wind_deg": 195, "wind_gust": 16.93, "weather": [{"id": 804, "main": "Clouds", "description": "overcast clouds", "icon": "04d"}], "pop": 0}, {"dt": 1620568800, "temp": 51.57, "feels_like": 50.18, "pressure": 1011, "humidity": 80, "dew_point": 45.73, "uvi": 3.09, "clouds": 98, "visibility": 10000, "wind_speed": 12.88, "wind_deg": 198, "wind_gust": 13.13, "weather": [{"id": 804, "main": "Clouds", "description": "overcast clouds", "icon": "04d"}], "pop": 0}, {"dt": 1620572400, "temp": 51.96, "feels_like": 50.58, "pressure": 1010, "humidity": 79, "dew_point": 46.09, "uvi": 1.9, "clouds": 99, "visibility": 10000, "wind_speed": 12.77, "wind_deg": 194, "wind_gust": 12.77, "weather": [{"id": 804, "main": "Clouds", "description": "overcast clouds", "icon": "04d"}], "pop": 0}, {"dt": 1620576000, "temp": 52.75, "feels_like": 51.44, "pressure": 1010, "humidity": 79, "dew_point": 46.63, "uvi": 0.93, "clouds": 99, "visibility": 10000, "wind_speed": 12.53, "wind_deg": 194, "wind_gust": 12.68, "weather": [{"id": 804, "main": "Clouds", "description": "overcast clouds", "icon": "04d"}], "pop": 0}, {"dt": 1620579600, "temp": 53.2, "feels_like": 51.89, "pressure": 1010, "humidity": 78, "dew_point": 46.81, "uvi": 0.37, "clouds": 97, "visibility": 10000, "wind_speed": 12.95, "wind_deg": 195, "wind_gust": 12.93, "weather": [{"id": 804, "main": "Clouds", "description": "overcast clouds", "icon": "04d"}], "pop": 0}, {"dt": 1620583200, "temp": 53.15, "feels_like": 51.84, "pressure": 1010, "humidity": 78, "dew_point": 46.71, "uvi": 0.1, "clouds": 93, "visibility": 10000, "wind_speed": 12.06, "wind_deg": 192, "wind_gust": 12.28, "weather": [{"id": 804, "main": "Clouds", "description": "overcast clouds", "icon": "04d"}], "pop": 0}, {"dt": 1620586800, "temp": 52.81, "feels_like": 51.49, "pressure": 1011, "humidity": 79, "dew_point": 46.76, "uvi": 0, "clouds": 29, "visibility": 10000, "wind_speed": 13.15, "wind_deg": 175, "wind_gust": 13.02, "weather": [{"id": 802, "main": "Clouds", "description": "scattered clouds", "icon": "03n"}], "pop": 0}, {"dt": 1620590400, "temp": 52.36, "feels_like": 51.19, "pressure": 1011, "humidity": 83, "dew_point": 47.61, "uvi": 0, "clouds": 43, "visibility": 10000, "wind_speed": 17.56, "wind_deg": 157, "wind_gust": 22.48, "weather": [{"id": 802, "main": "Clouds", "description": "scattered clouds", "icon": "03n"}], "pop": 0}, {"dt": 1620594000, "temp": 51.98, "feels_like": 50.88, "pressure": 1011, "humidity": 85, "dew_point": 47.82, "uvi": 0, "clouds": 57, "visibility": 10000, "wind_speed": 18.41, "wind_deg": 161, "wind_gust": 26.02, "weather": [{"id": 803, "main": "Clouds", "description": "broken clouds", "icon": "04n"}], "pop": 0}, {"dt": 1620597600, "temp": 51.19, "feels_like": 50.14, "pressure": 1011, "humidity": 88, "dew_point": 48.02, "uvi": 0, "clouds": 64, "visibility": 10000, "wind_speed": 17.47, "wind_deg": 161, "wind_gust": 25.66, "weather": [{"id": 803, "main": "Clouds", "description": "broken clouds", "icon": "04n"}], "pop": 0}, {"dt": 1620601200, "temp": 50.88, "feels_like": 49.86, "pressure": 1011, "humidity": 89, "dew_point": 47.84, "uvi": 0, "clouds": 56, "visibility": 10000, "wind_speed": 17.85, "wind_deg": 165, "wind_gust": 26.87, "weather": [{"id": 803, "main": "Clouds", "description": "broken clouds", "icon": "04n"}], "pop": 0}, {"dt": 1620604800, "temp": 50.29, "feels_like": 49.24, "pressure": 1010, "humidity": 90, "dew_point": 47.43, "uvi": 0, "clouds": 51, "visibility": 10000, "wind_speed": 18.28, "wind_deg": 166, "wind_gust": 28.34, "weather": [{"id": 803, "main": "Clouds", "description": "broken clouds", "icon": "04n"}], "pop": 0}, {"dt": 1620608400, "temp": 50.27, "feels_like": 49.14, "pressure": 1010, "humidity": 88, "dew_point": 47.12, "uvi": 0, "clouds": 39, "visibility": 10000, "wind_speed": 19.01, "wind_deg": 163, "wind_gust": 29.04, "weather": [{"id": 802, "main": "Clouds", "description": "scattered clouds", "icon": "03n"}], "pop": 0}, {"dt": 1620612000, "temp": 49.75, "feels_like": 43.57, "pressure": 1010, "humidity": 88, "dew_point": 46.36, "uvi": 0, "clouds": 68, "visibility": 10000, "wind_speed": 18.45, "wind_deg": 162, "wind_gust": 28.92, "weather": [{"id": 803, "main": "Clouds", "description": "broken clouds", "icon": "04n"}], "pop": 0}, {"dt": 1620615600, "temp": 49.35, "feels_like": 43.03, "pressure": 1010, "humidity": 86, "dew_point": 45.66, "uvi": 0, "clouds": 79, "visibility": 10000, "wind_speed": 18.52, "wind_deg": 162, "wind_gust": 30.29, "weather": [{"id": 803, "main": "Clouds", "description": "broken clouds", "icon": "04d"}], "pop": 0}, {"dt": 1620619200, "temp": 49.33, "feels_like": 42.75, "pressure": 1010, "humidity": 83, "dew_point": 44.53, "uvi": 0.13, "clouds": 84, "visibility": 10000, "wind_speed": 19.89, "wind_deg": 159, "wind_gust": 33.22, "weather": [{"id": 803, "main": "Clouds", "description": "broken clouds", "icon": "04d"}], "pop": 0}, {"dt": 1620622800, "temp": 49.35, "feels_like": 42.8, "pressure": 1010, "humidity": 82, "dew_point": 44.19, "uvi": 0.43, "clouds": 82, "visibility": 10000, "wind_speed": 19.73, "wind_deg": 163, "wind_gust": 34.05, "weather": [{"id": 803, "main": "Clouds", "description": "broken clouds", "icon": "04d"}], "pop": 0}, {"dt": 1620626400, "temp": 49.59, "feels_like": 43.7, "pressure": 1010, "humidity": 80, "dew_point": 44.08, "uvi": 1.05, "clouds": 85, "visibility": 10000, "wind_speed": 16.82, "wind_deg": 171, "wind_gust": 28.45, "weather": [{"id": 804, "main": "Clouds", "description": "overcast clouds", "icon": "04d"}], "pop": 0}, {"dt": 1620630000, "temp": 50.11, "feels_like": 48.58, "pressure": 1010, "humidity": 80, "dew_point": 44.22, "uvi": 2.15, "clouds": 88, "visibility": 10000, "wind_speed": 14.88, "wind_deg": 169, "wind_gust": 22.24, "weather": [{"id": 804, "main": "Clouds", "description": "overcast clouds", "icon": "04d"}], "pop": 0}, {"dt": 1620633600, "temp": 50.54, "feels_like": 49.01, "pressure": 1010, "humidity": 79, "dew_point": 44.35, "uvi": 3.38, "clouds": 56, "visibility": 10000, "wind_speed": 13.38, "wind_deg": 162, "wind_gust": 17.2, "weather": [{"id": 803, "main": "Clouds", "description": "broken clouds", "icon": "04d"}], "pop": 0}, {"dt": 1620637200, "temp": 51.01, "feels_like": 49.48, "pressure": 1010, "humidity": 78, "dew_point": 44.53, "uvi": 4.6, "clouds": 48, "visibility": 10000, "wind_speed": 11.65, "wind_deg": 154, "wind_gust": 12.01, "weather": [{"id": 802, "main": "Clouds", "description": "scattered clouds", "icon": "03d"}], "pop": 0}, {"dt": 1620640800, "temp": 51.69, "feels_like": 50.13, "pressure": 1010, "humidity": 76, "dew_point": 44.73, "uvi": 4.97, "clouds": 61, "visibility": 10000, "wind_speed": 10.74, "wind_deg": 149, "wind_gust": 10.83, "weather": [{"id": 803, "main": "Clouds", "description": "broken clouds", "icon": "04d"}], "pop": 0}, {"dt": 1620644400, "temp": 52.47, "feels_like": 50.88, "pressure": 1009, "humidity": 74, "dew_point": 44.78, "uvi": 5.23, "clouds": 69, "visibility": 10000, "wind_speed": 11.18, "wind_deg": 147, "wind_gust": 11.34, "weather": [{"id": 803, "main": "Clouds", "description": "broken clouds", "icon": "04d"}], "pop": 0}, {"dt": 1620648000, "temp": 53.29, "feels_like": 51.75, "pressure": 1009, "humidity": 73, "dew_point": 45.01, "uvi": 4.89, "clouds": 70, "visibility": 10000, "wind_speed": 11.27, "wind_deg": 149, "wind_gust": 11.43, "weather": [{"id": 803, "main": "Clouds", "description": "broken clouds", "icon": "04d"}], "pop": 0}, {"dt": 1620651600, "temp": 53.67, "feels_like": 52.18, "pressure": 1009, "humidity": 73, "dew_point": 45.73, "uvi": 4.29, "clouds": 20, "visibility": 10000, "wind_speed": 11.16, "wind_deg": 148, "wind_gust": 11.27, "weather": [{"id": 801, "main": "Clouds", "description": "few clouds", "icon": "02d"}], "pop": 0}, {"dt": 1620655200, "temp": 53.98, "feels_like": 52.59, "pressure": 1009, "humidity": 75, "dew_point": 46.45, "uvi": 3.1, "clouds": 60, "visibility": 10000, "wind_speed": 11.34, "wind_deg": 166, "wind_gust": 11.65, "weather": [{"id": 803, "main": "Clouds", "description": "broken clouds", "icon": "04d"}], "pop": 0}, {"dt": 1620658800, "temp": 54.48, "feels_like": 53.15, "pressure": 1009, "humidity": 75, "dew_point": 47.03, "uvi": 1.91, "clouds": 73, "visibility": 10000, "wind_speed": 11.21, "wind_deg": 182, "wind_gust": 11.54, "weather": [{"id": 803, "main": "Clouds", "description": "broken clouds", "icon": "04d"}], "pop": 0}, {"dt": 1620662400, "temp": 55, "feels_like": 53.78, "pressure": 1009, "humidity": 76, "dew_point": 47.68, "uvi": 1.02, "clouds": 79, "visibility": 10000, "wind_speed": 13.18, "wind_deg": 181, "wind_gust": 13.27, "weather": [{"id": 803, "main": "Clouds", "description": "broken clouds", "icon": "04d"}], "pop": 0}], "daily": [{"dt": 1620468000, "sunrise": 1620442914, "sunset": 1620499343, "moonrise": 1620441240, "moonset": 1620485520, "moon_phase": 0.9, "temp": {"day": 42.87, "min": 41.94, "max": 44.33, "night": 44.33, "eve": 44.01, "morn": 43.05}, "feels_like": {"day": 34.56, "night": 35.31, "eve": 37.8, "morn": 35.31}, "pressure": 1015, "humidity": 88, "dew_point": 39.83, "wind_speed": 19.51, "wind_deg": 268, "wind_gust": 24.34, "weather": [{"id": 500, "main": "Rain", "description": "light rain", "icon": "10d"}], "clouds": 20, "pop": 0.56, "rain": 1.1, "uvi": 4.33}, {"dt": 1620554400, "sunrise": 1620529199, "sunset": 1620585854, "moonrise": 1620528240, "moonset": 1620576300, "moon_phase": 0.93, "temp": {"day": 47.73, "min": 43.79, "max": 53.2, "night": 51.98, "eve": 52.75, "morn": 44.67}, "feels_like": {"day": 41.31, "night": 36.57, "eve": 51.44, "morn": 36.57}, "pressure": 1011, "humidity": 80, "dew_point": 42.06, "wind_speed": 23.76, "wind_deg": 158, "wind_gust": 37.31, "weather": [{"id": 500, "main": "Rain", "description": "light rain", "icon": "10d"}], "clouds": 100, "pop": 0.93, "rain": 1.46, "uvi": 5.61}, {"dt": 1620640800, "sunrise": 1620615485, "sunset": 1620672365, "moonrise": 1620615300, "moonset": 1620667020, "moon_phase": 0.96, "temp": {"day": 51.69, "min": 49.33, "max": 55, "night": 51.39, "eve": 55, "morn": 49.33}, "feels_like": {"day": 50.13, "night": 42.75, "eve": 53.78, "morn": 42.75}, "pressure": 1010, "humidity": 76, "dew_point": 44.73, "wind_speed": 19.89, "wind_deg": 159, "wind_gust": 34.05, "weather": [{"id": 803, "main": "Clouds", "description": "broken clouds", "icon": "04d"}], "clouds": 61, "pop": 0, "uvi": 5.23}, {"dt": 1620727200, "sunrise": 1620701773, "sunset": 1620758875, "moonrise": 1620702420, "moonset": 1620757800, "moon_phase": 0, "temp": {"day": 52.29, "min": 47.34, "max": 55.56, "night": 55.56, "eve": 54.82, "morn": 48.25}, "feels_like": {"day": 51.3, "night": 44.73, "eve": 53.76, "morn": 44.73}, "pressure": 1009, "humidity": 87, "dew_point": 48.74, "wind_speed": 11.48, "wind_deg": 124, "wind_gust": 11.45, "weather": [{"id": 804, "main": "Clouds", "description": "overcast clouds", "icon": "04d"}], "clouds": 100, "pop": 0, "uvi": 5.47}, {"dt": 1620813600, "sunrise": 1620788063, "sunset": 1620845384, "moonrise": 1620789720, "moonset": 1620848580, "moon_phase": 0.02, "temp": {"day": 51.58, "min": 47.39, "max": 55.04, "night": 47.39, "eve": 55.04, "morn": 51.96}, "feels_like": {"day": 50.43, "night": 51.22, "eve": 53.91, "morn": 51.22}, "pressure": 1007, "humidity": 85, "dew_point": 47.21, "wind_speed": 17.2, "wind_deg": 134, "wind_gust": 25.64, "weather": [{"id": 800, "main": "Clear", "description": "clear sky", "icon": "01d"}], "clouds": 0, "pop": 0.06, "uvi": 5.71}, {"dt": 1620900000, "sunrise": 1620874355, "sunset": 1620931893, "moonrise": 1620877260, "moonset": 1620939240, "moon_phase": 0.05, "temp": {"day": 48.52, "min": 46.38, "max": 48.52, "night": 46.38, "eve": 48.38, "morn": 46.63}, "feels_like": {"day": 43.97, "night": 42.6, "eve": 41.67, "morn": 42.6}, "pressure": 1010, "humidity": 85, "dew_point": 44.31, "wind_speed": 19.04, "wind_deg": 58, "wind_gust": 28.01, "weather": [{"id": 800, "main": "Clear", "description": "clear sky", "icon": "01d"}], "clouds": 4, "pop": 0, "uvi": 6}, {"dt": 1620986400, "sunrise": 1620960649, "sunset": 1621018400, "moonrise": 1620965220, "moonset": 0, "moon_phase": 0.08, "temp": {"day": 46.33, "min": 44.98, "max": 47.32, "night": 47.21, "eve": 46.49, "morn": 45.9}, "feels_like": {"day": 40.77, "night": 41.79, "eve": 40.14, "morn": 41.79}, "pressure": 1005, "humidity": 88, "dew_point": 43.05, "wind_speed": 16.11, "wind_deg": 242, "wind_gust": 23.96, "weather": [{"id": 804, "main": "Clouds", "description": "overcast clouds", "icon": "04d"}], "clouds": 100, "pop": 0.17, "uvi": 6}, {"dt": 1621072800, "sunrise": 1621046944, "sunset": 1621104907, "moonrise": 1621053780, "moonset": 1621029660, "moon_phase": 0.11, "temp": {"day": 46.58, "min": 46.38, "max": 47.14, "night": 46.76, "eve": 46.85, "morn": 46.99}, "feels_like": {"day": 39.42, "night": 39.76, "eve": 39.36, "morn": 39.76}, "pressure": 1009, "humidity": 93, "dew_point": 44.83, "wind_speed": 21.79, "wind_deg": 245, "wind_gust": 33.24, "weather": [{"id": 500, "main": "Rain", "description": "light rain", "icon": "10d"}], "clouds": 99, "pop": 0.35, "rain": 0.82, "uvi": 6}]}