{"lat": 53.878, "lon": 9.7945, "timezone": "Europe/Berlin", "timezone_offset": 7200, "current": {"dt": 1620500148, "sunrise": 1620444647, "sunset": 1620500630, "temp": 50, "feels_like": 48.22, "pressure": 1014, "humidity": 73, "dew_point": 41.7, "uvi": 0, "clouds": 100, "visibility": 10000, "wind_speed": 5.01, "wind_deg": 292, "wind_gust": 5.01, "weather": [{"id": 500, "main": "Rain", "description": "light rain", "icon": "10d"}], "rain": {"1h": 0.6}}, "minutely": [{"dt": 1620500160, "precipitation": 0.5994}, {"dt": 1620500220, "precipitation": 0.6368}, {"dt": 1620500280, "precipitation": 0.6742}, {"dt": 1620500340, "precipitation": 0.7116}, {"dt": 1620500400, "precipitation": 0.749}, {"dt": 1620500460, "precipitation": 0.7722}, {"dt": 1620500520, "precipitation": 0.7954}, {"dt": 1620500580, "precipitation": 0.8186}, {"dt": 1620500640, "precipitation": 0.8418}, {"dt": 1620500700, "precipitation": 0.865}, {"dt": 1620500760, "precipitation": 0.9226}, {"dt": 1620500820, "precipitation": 0.9802}, {"dt": 1620500880, "precipitation": 1.0378}, {"dt": 1620500940, "precipitation": 1.0954}, {"dt": 1620501000, "precipitation": 1.153}, {"dt": 1620501060, "precipitation": 1.2776}, {"dt": 1620501120, "precipitation": 1.4022}, {"dt": 1620501180, "precipitation": 1.5268}, {"dt": 1620501240, "precipitation": 1.6514}, {"dt": 1620501300, "precipitation": 1.776}, {"dt": 1620501360, "precipitation": 1.8944}, {"dt": 1620501420, "precipitation": 2.0128}, {"dt": 1620501480, "precipitation": 2.1312}, {"dt": 1620501540, "precipitation": 2.2496}, {"dt": 1620501600, "precipitation": 2.368}, {"dt": 1620501660, "precipitation": 2.4412}, {"dt": 1620501720, "precipitation": 2.5144}, {"dt": 1620501780, "precipitation": 2.5876}, {"dt": 1620501840, "precipitation": 2.6608}, {"dt": 1620501900, "precipitation": 2.734}, {"dt": 1620501960, "precipitation": 2.734}, {"dt": 1620502020, "precipitation": 2.734}, {"dt": 1620502080, "precipitation": 2.734}, {"dt": 1620502140, "precipitation": 2.734}, {"dt": 1620502200, "precipitation": 2.734}, {"dt": 1620502260, "precipitation": 2.5972}, {"dt": 1620502320, "precipitation": 2.4604}, {"dt": 1620502380, "precipitation": 2.3236}, {"dt": 1620502440, "precipitation": 2.1868}, {"dt": 1620502500, "precipitation": 2.05}, {"dt": 1620502560, "precipitation": 1.9476}, {"dt": 1620502620, "precipitation": 1.8452}, {"dt": 1620502680, "precipitation": 1.7428}, {"dt": 1620502740, "precipitation": 1.6404}, {"dt": 1620502800, "precipitation": 1.538}, {"dt": 1620502860, "precipitation": 1.538}, {"dt": 1620502920, "precipitation": 1.538}, {"dt": 1620502980, "precipitation": 1.538}, {"dt": 1620503040, "precipitation": 1.538}, {"dt": 1620503100, "precipitation": 1.538}, {"dt": 1620503160, "precipitation": 1.5856}, {"dt": 1620503220, "precipitation": 1.6332}, {"dt": 1620503280, "precipitation": 1.6808}, {"dt": 1620503340, "precipitation": 1.7284}, {"dt": 1620503400, "precipitation": 1.776}, {"dt": 1620503460, "precipitation": 1.776}, {"dt": 1620503520, "precipitation": 1.776}, {"dt": 1620503580, "precipitation": 1.776}, {"dt": 1620503640, "precipitation": 1.776}, {"dt": 1620503700, "precipitation": 1.776}, {"dt": 1620503760, "precipitation": 1.776}], "hourly": [{"dt": 1620496800, "temp": 49.66, "feels_like": 45.48, "pressure": 1014, "humidity": 72, "dew_point": 41.02, "uvi": 0.08, "clouds": 100, "visibility": 10000, "wind_speed": 10.38, "wind_deg": 169, "wind_gust": 19.95, "weather": [{"id": 500, "main": "Rain", "description": "light rain", "icon": "10d"}], "pop": 0.39, "rain": {"1h": 0.16}}, {"dt": 1620500400, "temp": 50, "feels_like": 45.54, "pressure": 1014, "humidity": 73, "dew_point": 41.7, "uvi": 0, "clouds": 100, "visibility": 10000, "wind_speed": 11.63, "wind_deg": 150, "wind_gust": 26.17, "weather": [{"id": 500, "main": "Rain", "description": "light rain", "icon": "10d"}], "pop": 0.78, "rain": {"1h": 0.75}}, {"dt": 1620504000, "temp": 49.12, "feels_like": 43.79, "pressure": 1013, "humidity": 77, "dew_point": 42.22, "uvi": 0, "clouds": 100, "visibility": 10000, "wind_speed": 13.87, "wind_deg": 157, "wind_gust": 31.61, "weather": [{"id": 501, "main": "Rain", "description": "moderate rain", "icon": "10n"}], "pop": 0.98, "rain": {"1h": 1.78}}, {"dt": 1620507600, "temp": 48.38, "feels_like": 42.28, "pressure": 1012, "humidity": 82, "dew_point": 43.14, "uvi": 0, "clouds": 100, "visibility": 10000, "wind_speed": 16.22, "wind_deg": 162, "wind_gust": 34.23, "weather": [{"id": 501, "main": "Rain", "description": "moderate rain", "icon": "10n"}], "pop": 1, "rain": {"1h": 1.33}}, {"dt": 1620511200, "temp": 47.7, "feels_like": 41.63, "pressure": 1010, "humidity": 87, "dew_point": 44.02, "uvi": 0, "clouds": 100, "visibility": 8005, "wind_speed": 15.26, "wind_deg": 169, "wind_gust": 33.73, "weather": [{"id": 501, "main": "Rain", "description": "moderate rain", "icon": "10n"}], "pop": 1, "rain": {"1h": 1.22}}, {"dt": 1620514800, "temp": 47.73, "feels_like": 41.88, "pressure": 1009, "humidity": 89, "dew_point": 44.65, "uvi": 0, "clouds": 100, "visibility": 10000, "wind_speed": 14.45, "wind_deg": 175, "wind_gust": 33.82, "weather": [{"id": 500, "main": "Rain", "description": "light rain", "icon": "10n"}], "pop": 1, "rain": {"1h": 0.63}}, {"dt": 1620518400, "temp": 48.43, "feels_like": 43.05, "pressure": 1007, "humidity": 93, "dew_point": 46.69, "uvi": 0, "clouds": 100, "visibility": 10000, "wind_speed": 13.38, "wind_deg": 185, "wind_gust": 33.42, "weather": [{"id": 804, "main": "Clouds", "description": "overcast clouds", "icon": "04n"}], "pop": 0.8}, {"dt": 1620522000, "temp": 49.17, "feels_like": 44.19, "pressure": 1007, "humidity": 94, "dew_point": 47.73, "uvi": 0, "clouds": 100, "visibility": 10000, "wind_speed": 12.66, "wind_deg": 191, "wind_gust": 32.88, "weather": [{"id": 804, "main": "Clouds", "description": "overcast clouds", "icon": "04n"}], "pop": 0.04}, {"dt": 1620525600, "temp": 50.58, "feels_like": 49.75, "pressure": 1007, "humidity": 94, "dew_point": 49.23, "uvi": 0, "clouds": 100, "visibility": 10000, "wind_speed": 11.83, "wind_deg": 196, "wind_gust": 31.21, "weather": [{"id": 804, "main": "Clouds", "description": "overcast clouds", "icon": "04n"}], "pop": 0.02}, {"dt": 1620529200, "temp": 49.98, "feels_like": 45.64, "pressure": 1006, "humidity": 95, "dew_point": 48.99, "uvi": 0, "clouds": 100, "visibility": 10000, "wind_speed": 11.16, "wind_deg": 193, "wind_gust": 28.52, "weather": [{"id": 804, "main": "Clouds", "description": "overcast clouds", "icon": "04n"}], "pop": 0.02}, {"dt": 1620532800, "temp": 48.97, "feels_like": 44.58, "pressure": 1006, "humidity": 96, "dew_point": 48.25, "uvi": 0, "clouds": 99, "visibility": 10000, "wind_speed": 10.56, "wind_deg": 187, "wind_gust": 27.4, "weather": [{"id": 804, "main": "Clouds", "description": "overcast clouds", "icon": "04d"}], "pop": 0}, {"dt": 1620536400, "temp": 50.22, "feels_like": 49.41, "pressure": 1006, "humidity": 95, "dew_point": 49.24, "uvi": 0.26, "clouds": 94, "visibility": 10000, "wind_speed": 10.2, "wind_deg": 187, "wind_gust": 27.47, "weather": [{"id": 804, "main": "Clouds", "description": "overcast clouds", "icon": "04d"}], "pop": 0}, {"dt": 1620540000, "temp": 53.56, "feels_like": 52.95, "pressure": 1007, "humidity": 92, "dew_point": 51.58, "uvi": 0.75, "clouds": 95, "visibility": 10000, "wind_speed": 10.47, "wind_deg": 192, "wind_gust": 27.04, "weather": [{"id": 804, "main": "Clouds", "description": "overcast clouds", "icon": "04d"}], "pop": 0}, {"dt": 1620543600, "temp": 57.02, "feels_like": 56.46, "pressure": 1007, "humidity": 86, "dew_point": 53.19, "uvi": 1.71, "clouds": 97, "visibility": 10000, "wind_speed": 11.32, "wind_deg": 197, "wind_gust": 23.02, "weather": [{"id": 804, "main": "Clouds", "description": "overcast clouds", "icon": "04d"}], "pop": 0}, {"dt": 1620547200, "temp": 60.87, "feels_like": 60.33, "pressure": 1007, "humidity": 78, "dew_point": 54.46, "uvi": 2.96, "clouds": 94, "visibility": 10000, "wind_speed": 11.61, "wind_deg": 196, "wind_gust": 19.75, "weather": [{"id": 804, "main": "Clouds", "description": "overcast clouds", "icon": "04d"}], "pop": 0}, {"dt": 1620550800, "temp": 64.51, "feels_like": 63.95, "pressure": 1006, "humidity": 70, "dew_point": 54.91, "uvi": 4.32, "clouds": 96, "visibility": 10000, "wind_speed": 12.03, "wind_deg": 190, "wind_gust": 19.28, "weather": [{"id": 804, "main": "Clouds", "description": "overcast clouds", "icon": "04d"}], "pop": 0}, {"dt": 1620554400, "temp": 67.6, "feels_like": 66.94, "pressure": 1006, "humidity": 61, "dew_point": 54.09, "uvi": 5.21, "clouds": 95, "visibility": 10000, "wind_speed": 12.53, "wind_deg": 183, "wind_gust": 18.84, "weather": [{"id": 804, "main": "Clouds", "description": "overcast clouds", "icon": "04d"}], "pop": 0}, {"dt": 1620558000, "temp": 69.55, "feels_like": 68.88, "pressure": 1006, "humidity": 57, "dew_point": 53.92, "uvi": 5.79, "clouds": 95, "visibility": 10000, "wind_speed": 13.04, "wind_deg": 188, "wind_gust": 21.12, "weather": [{"id": 804, "main": "Clouds", "description": "overcast clouds", "icon": "04d"}], "pop": 0}, {"dt": 1620561600, "temp": 66.97, "feels_like": 66.43, "pressure": 1006, "humidity": 65, "dew_point": 55.17, "uvi": 5.69, "clouds": 96, "visibility": 10000, "wind_speed": 12.64, "wind_deg": 190, "wind_gust": 22.95, "weather": [{"id": 804, "main": "Clouds", "description": "overcast clouds", "icon": "04d"}], "pop": 0}, {"dt": 1620565200, "temp": 65.68, "feels_like": 65.34, "pressure": 1005, "humidity": 72, "dew_point": 56.97, "uvi": 1.58, "clouds": 100, "visibility": 10000, "wind_speed": 7.61, "wind_deg": 190, "wind_gust": 19.42, "weather": [{"id": 804, "main": "Clouds", "description": "overcast clouds", "icon": "04d"}], "pop": 0.03}, {"dt": 1620568800, "temp": 66.42, "feels_like": 66.15, "pressure": 1005, "humidity": 72, "dew_point": 57.27, "uvi": 1.21, "clouds": 100, "visibility": 10000, "wind_speed": 6.11, "wind_deg": 187, "wind_gust": 12.55, "weather": [{"id": 804, "main": "Clouds", "description": "overcast clouds", "icon": "04d"}], "pop": 0.16}, {"dt": 1620572400, "temp": 69.64, "feels_like": 69.49, "pressure": 1004, "humidity": 68, "dew_point": 58.75, "uvi": 0.79, "clouds": 98, "visibility": 10000, "wind_speed": 5.86, "wind_deg": 160, "wind_gust": 14.58, "weather": [{"id": 804, "main": "Clouds", "description": "overcast clouds", "icon": "04d"}], "pop": 0.21}, {"dt": 1620576000, "temp": 71.58, "feels_like": 71.55, "pressure": 1003, "humidity": 66, "dew_point": 60.1, "uvi": 1.14, "clouds": 94, "visibility": 10000, "wind_speed": 10.11, "wind_deg": 163, "wind_gust": 22.08, "weather": [{"id": 804, "main": "Clouds", "description": "overcast clouds", "icon": "04d"}], "pop": 0.17}, {"dt": 1620579600, "temp": 69.75, "feels_like": 69.71, "pressure": 1003, "humidity": 70, "dew_point": 59.85, "uvi": 0.5, "clouds": 92, "visibility": 10000, "wind_speed": 9.64, "wind_deg": 176, "wind_gust": 23.11, "weather": [{"id": 804, "main": "Clouds", "description": "overcast clouds", "icon": "04d"}], "pop": 0.17}, {"dt": 1620583200, "temp": 66.96, "feels_like": 66.78, "pressure": 1003, "humidity": 73, "dew_point": 58.39, "uvi": 0.16, "clouds": 93, "visibility": 10000, "wind_speed": 9.22, "wind_deg": 167, "wind_gust": 24.72, "weather": [{"id": 804, "main": "Clouds", "description": "overcast clouds", "icon": "04d"}], "pop": 0.17}, {"dt": 1620586800, "temp": 64.58, "feels_like": 64.22, "pressure": 1003, "humidity": 74, "dew_point": 56.32, "uvi": 0, "clouds": 86, "visibility": 10000, "wind_speed": 10.02, "wind_deg": 155, "wind_gust": 27.69, "weather": [{"id": 804, "main": "Clouds", "description": "overcast clouds", "icon": "04d"}], "pop": 0}, {"dt": 1620590400, "temp": 62.98, "feels_like": 62.4, "pressure": 1003, "humidity": 73, "dew_point": 54.64, "uvi": 0, "clouds": 93, "visibility": 10000, "wind_speed": 10.87, "wind_deg": 157, "wind_gust": 30.62, "weather": [{"id": 804, "main": "Clouds", "description": "overcast clouds", "icon": "04n"}], "pop": 0}, {"dt": 1620594000, "temp": 60.89, "feels_like": 60.39, "pressure": 1003, "humidity": 79, "dew_point": 54.7, "uvi": 0, "clouds": 81, "visibility": 10000, "wind_speed": 10.36, "wind_deg": 162, "wind_gust": 29.55, "weather": [{"id": 500, "main": "Rain", "description": "light rain", "icon": "10n"}], "pop": 0.24, "rain": {"1h": 0.17}}, {"dt": 1620597600, "temp": 59.49, "feels_like": 59.04, "pressure": 1003, "humidity": 83, "dew_point": 54.64, "uvi": 0, "clouds": 86, "visibility": 10000, "wind_speed": 8.79, "wind_deg": 164, "wind_gust": 25.99, "weather": [{"id": 804, "main": "Clouds", "description": "overcast clouds", "icon": "04n"}], "pop": 0.04}, {"dt": 1620601200, "temp": 58.48, "feels_like": 58.06, "pressure": 1003, "humidity": 86, "dew_point": 54.59, "uvi": 0, "clouds": 89, "visibility": 10000, "wind_speed": 8.39, "wind_deg": 164, "wind_gust": 25.34, "weather": [{"id": 804, "main": "Clouds", "description": "overcast clouds", "icon": "04n"}], "pop": 0}, {"dt": 1620604800, "temp": 58.39, "feels_like": 57.92, "pressure": 1003, "humidity": 85, "dew_point": 54.12, "uvi": 0, "clouds": 91, "visibility": 10000, "wind_speed": 8.3, "wind_deg": 167, "wind_gust": 24.99, "weather": [{"id": 804, "main": "Clouds", "description": "overcast clouds", "icon": "04n"}], "pop": 0}, {"dt": 1620608400, "temp": 57.49, "feels_like": 56.84, "pressure": 1003, "humidity": 83, "dew_point": 52.65, "uvi": 0, "clouds": 98, "visibility": 10000, "wind_speed": 8.23, "wind_deg": 172, "wind_gust": 25.26, "weather": [{"id": 804, "main": "Clouds", "description": "overcast clouds", "icon": "04n"}], "pop": 0}, {"dt": 1620612000, "temp": 55.92, "feels_like": 55.17, "pressure": 1003, "humidity": 84, "dew_point": 51.4, "uvi": 0, "clouds": 65, "visibility": 10000, "wind_speed": 7.78, "wind_deg": 171, "wind_gust": 22.5, "weather": [{"id": 803, "main": "Clouds", "description": "broken clouds", "icon": "04n"}], "pop": 0}, {"dt": 1620615600, "temp": 54.93, "feels_like": 54.18, "pressure": 1003, "humidity": 86, "dew_point": 51.3, "uvi": 0, "clouds": 75, "visibility": 10000, "wind_speed": 8.05, "wind_deg": 168, "wind_gust": 23.71, "weather": [{"id": 803, "main": "Clouds", "description": "broken clouds", "icon": "04n"}], "pop": 0}, {"dt": 1620619200, "temp": 55.26, "feels_like": 54.57, "pressure": 1003, "humidity": 87, "dew_point": 51.78, "uvi": 0, "clouds": 81, "visibility": 10000, "wind_speed": 6.96, "wind_deg": 167, "wind_gust": 19.06, "weather": [{"id": 803, "main": "Clouds", "description": "broken clouds", "icon": "04d"}], "pop": 0}, {"dt": 1620622800, "temp": 57.6, "feels_like": 57.06, "pressure": 1003, "humidity": 85, "dew_point": 53.56, "uvi": 0.19, "clouds": 85, "visibility": 10000, "wind_speed": 8.59, "wind_deg": 152, "wind_gust": 17.65, "weather": [{"id": 804, "main": "Clouds", "description": "overcast clouds", "icon": "04d"}], "pop": 0}, {"dt": 1620626400, "temp": 60.6, "feels_like": 60.26, "pressure": 1003, "humidity": 83, "dew_point": 55.6, "uvi": 0.52, "clouds": 87, "visibility": 10000, "wind_speed": 7.43, "wind_deg": 151, "wind_gust": 16.06, "weather": [{"id": 804, "main": "Clouds", "description": "overcast clouds", "icon": "04d"}], "pop": 0}, {"dt": 1620630000, "temp": 63.12, "feels_like": 62.85, "pressure": 1004, "humidity": 79, "dew_point": 56.86, "uvi": 1.32, "clouds": 100, "visibility": 10000, "wind_speed": 7.76, "wind_deg": 155, "wind_gust": 15.46, "weather": [{"id": 804, "main": "Clouds", "description": "overcast clouds", "icon": "04d"}], "pop": 0}, {"dt": 1620633600, "temp": 65.8, "feels_like": 65.46, "pressure": 1004, "humidity": 72, "dew_point": 56.91, "uvi": 2.28, "clouds": 100, "visibility": 10000, "wind_speed": 7.65, "wind_deg": 182, "wind_gust": 13.6, "weather": [{"id": 804, "main": "Clouds", "description": "overcast clouds", "icon": "04d"}], "pop": 0}, {"dt": 1620637200, "temp": 69.26, "feels_like": 68.9, "pressure": 1004, "humidity": 64, "dew_point": 57.04, "uvi": 3.31, "clouds": 100, "visibility": 10000, "wind_speed": 10, "wind_deg": 183, "wind_gust": 16.28, "weather": [{"id": 804, "main": "Clouds", "description": "overcast clouds", "icon": "04d"}], "pop": 0}, {"dt": 1620640800, "temp": 70.47, "feels_like": 70.09, "pressure": 1003, "humidity": 61, "dew_point": 56.84, "uvi": 4.09, "clouds": 100, "visibility": 10000, "wind_speed": 8.68, "wind_deg": 209, "wind_gust": 12.08, "weather": [{"id": 804, "main": "Clouds", "description": "overcast clouds", "icon": "04d"}], "pop": 0}, {"dt": 1620644400, "temp": 70.27, "feels_like": 69.96, "pressure": 1003, "humidity": 63, "dew_point": 57.36, "uvi": 4.54, "clouds": 100, "visibility": 10000, "wind_speed": 10.13, "wind_deg": 235, "wind_gust": 11.5, "weather": [{"id": 804, "main": "Clouds", "description": "overcast clouds", "icon": "04d"}], "pop": 0}, {"dt": 1620648000, "temp": 66.61, "feels_like": 66.51, "pressure": 1004, "humidity": 75, "dew_point": 58.91, "uvi": 4.47, "clouds": 100, "visibility": 10000, "wind_speed": 15.26, "wind_deg": 245, "wind_gust": 18.92, "weather": [{"id": 500, "main": "Rain", "description": "light rain", "icon": "10d"}], "pop": 0.28, "rain": {"1h": 0.31}}, {"dt": 1620651600, "temp": 60.84, "feels_like": 60.66, "pressure": 1006, "humidity": 86, "dew_point": 56.97, "uvi": 1.87, "clouds": 100, "visibility": 10000, "wind_speed": 17.78, "wind_deg": 241, "wind_gust": 29.64, "weather": [{"id": 500, "main": "Rain", "description": "light rain", "icon": "10d"}], "pop": 0.86, "rain": {"1h": 0.31}}, {"dt": 1620655200, "temp": 58.41, "feels_like": 57.85, "pressure": 1007, "humidity": 83, "dew_point": 53.35, "uvi": 1.43, "clouds": 100, "visibility": 10000, "wind_speed": 15.28, "wind_deg": 261, "wind_gust": 26.87, "weather": [{"id": 804, "main": "Clouds", "description": "overcast clouds", "icon": "04d"}], "pop": 0.75}, {"dt": 1620658800, "temp": 59.27, "feels_like": 58.51, "pressure": 1009, "humidity": 77, "dew_point": 52.5, "uvi": 0.94, "clouds": 100, "visibility": 10000, "wind_speed": 13.89, "wind_deg": 261, "wind_gust": 22.01, "weather": [{"id": 804, "main": "Clouds", "description": "overcast clouds", "icon": "04d"}], "pop": 0.58}, {"dt": 1620662400, "temp": 59.36, "feels_like": 58.62, "pressure": 1009, "humidity": 77, "dew_point": 52.39, "uvi": 1.19, "clouds": 100, "visibility": 10000, "wind_speed": 9.75, "wind_deg": 275, "wind_gust": 15.66, "weather": [{"id": 804, "main": "Clouds", "description": "overcast clouds", "icon": "04d"}], "pop": 0.58}, {"dt": 1620666000, "temp": 58.14, "feels_like": 57.51, "pressure": 1009, "humidity": 82, "dew_point": 53.2, "uvi": 0.53, "clouds": 100, "visibility": 10000, "wind_speed": 5.99, "wind_deg": 278, "wind_gust": 13.11, "weather": [{"id": 804, "main": "Clouds", "description": "overcast clouds", "icon": "04d"}], "pop": 0.45}], "daily": [{"dt": 1620471600, "sunrise": 1620444647, "sunset": 1620500630, "moonrise": 1620442740, "moonset": 1620487140, "moon_phase": 0.9, "temp": {"day": 51.67, "min": 34.39, "max": 54.05, "night": 48.38, "eve": 50.45, "morn": 37.06}, "feels_like": {"day": 49.03, "night": 32.13, "eve": 48.4, "morn": 32.13}, "pressure": 1016, "humidity": 53, "dew_point": 35.73, "wind_speed": 16.22, "wind_deg": 162, "wind_gust": 34.23, "weather": [{"id": 501, "main": "Rain", "description": "moderate rain", "icon": "10d"}], "clouds": 81, "pop": 1, "rain": 4.02, "uvi": 4.33}, {"dt": 1620558000, "sunrise": 1620530936, "sunset": 1620587137, "moonrise": 1620529860, "moonset": 1620577800, "moon_phase": 0.93, "temp": {"day": 69.55, "min": 47.7, "max": 71.58, "night": 60.89, "eve": 69.75, "morn": 50.22}, "feels_like": {"day": 68.88, "night": 49.41, "eve": 69.71, "morn": 49.41}, "pressure": 1006, "humidity": 57, "dew_point": 53.92, "wind_speed": 15.26, "wind_deg": 169, "wind_gust": 33.82, "weather": [{"id": 501, "main": "Rain", "description": "moderate rain", "icon": "10d"}], "clouds": 95, "pop": 1, "rain": 2.02, "uvi": 5.79}, {"dt": 1620644400, "sunrise": 1620617227, "sunset": 1620673643, "moonrise": 1620616920, "moonset": 1620668460, "moon_phase": 0.96, "temp": {"day": 70.27, "min": 52.38, "max": 70.47, "night": 52.38, "eve": 58.14, "morn": 57.6}, "feels_like": {"day": 69.96, "night": 57.06, "eve": 57.51, "morn": 57.06}, "pressure": 1003, "humidity": 63, "dew_point": 57.36, "wind_speed": 17.78, "wind_deg": 241, "wind_gust": 29.64, "weather": [{"id": 500, "main": "Rain", "description": "light rain", "icon": "10d"}], "clouds": 100, "pop": 0.86, "rain": 0.62, "uvi": 4.54}, {"dt": 1620730800, "sunrise": 1620703520, "sunset": 1620760149, "moonrise": 1620704160, "moonset": 1620759180, "moon_phase": 0, "temp": {"day": 53.64, "min": 46.24, "max": 54.63, "night": 46.24, "eve": 51.21, "morn": 49.37}, "feels_like": {"day": 52.59, "night": 46.83, "eve": 50.02, "morn": 46.83}, "pressure": 1011, "humidity": 83, "dew_point": 48.79, "wind_speed": 12.21, "wind_deg": 42, "wind_gust": 17.36, "weather": [{"id": 501, "main": "Rain", "description": "moderate rain", "icon": "10d"}], "clouds": 100, "pop": 1, "rain": 19.76, "uvi": 2.71}, {"dt": 1620817200, "sunrise": 1620789814, "sunset": 1620846653, "moonrise": 1620791460, "moonset": 1620849900, "moon_phase": 0.02, "temp": {"day": 51.39, "min": 44.67, "max": 51.55, "night": 44.85, "eve": 51.55, "morn": 47.21}, "feels_like": {"day": 50.45, "night": 44.91, "eve": 50.4, "morn": 44.91}, "pressure": 1009, "humidity": 90, "dew_point": 48.99, "wind_speed": 11.03, "wind_deg": 285, "wind_gust": 21.25, "weather": [{"id": 501, "main": "Rain", "description": "moderate rain", "icon": "10d"}], "clouds": 100, "pop": 1, "rain": 5.92, "uvi": 0.8}, {"dt": 1620903600, "sunrise": 1620876110, "sunset": 1620933157, "moonrise": 1620879060, "moonset": 1620940500, "moon_phase": 0.05, "temp": {"day": 52.09, "min": 44.24, "max": 53.44, "night": 48.42, "eve": 49.41, "morn": 48.34}, "feels_like": {"day": 51.22, "night": 45.63, "eve": 47.35, "morn": 45.63}, "pressure": 1011, "humidity": 90, "dew_point": 49.57, "wind_speed": 8.25, "wind_deg": 351, "wind_gust": 17.25, "weather": [{"id": 500, "main": "Rain", "description": "light rain", "icon": "10d"}], "clouds": 100, "pop": 0.41, "rain": 0.49, "uvi": 0.74}, {"dt": 1620990000, "sunrise": 1620962409, "sunset": 1621019660, "moonrise": 1620967140, "moonset": 0, "moon_phase": 0.08, "temp": {"day": 56.55, "min": 43.86, "max": 56.55, "night": 43.86, "eve": 50.85, "morn": 47.98}, "feels_like": {"day": 55.06, "night": 46.04, "eve": 49.53, "morn": 46.04}, "pressure": 1009, "humidity": 67, "dew_point": 46.15, "wind_speed": 11.52, "wind_deg": 284, "wind_gust": 19.48, "weather": [{"id": 804, "main": "Clouds", "description": "overcast clouds", "icon": "04d"}], "clouds": 94, "pop": 0, "uvi": 1}, {"dt": 1621076400, "sunrise": 1621048709, "sunset": 1621106162, "moonrise": 1621055760, "moonset": 1621030800, "moon_phase": 0.11, "temp": {"day": 54.66, "min": 43.7, "max": 54.66, "night": 48.04, "eve": 48.45, "morn": 46.67}, "feels_like": {"day": 52.97, "night": 41.49, "eve": 43.36, "morn": 41.49}, "pressure": 1014, "humidity": 67, "dew_point": 44.56, "wind_speed": 13.76, "wind_deg": 276, "wind_gust": 18.21, "weather": [{"id": 803, "main": "Clouds", "description": "broken clouds", "icon": "04d"}], "clouds": 80, "pop": 0, "uvi": 1}]}